tree_utils/__init__.py
tree_utils/_tree_utils.py
tree_utils/tree_dataloader.py
imt_tree_utils-0.2.7.dist-info/METADATA
imt_tree_utils-0.2.7.dist-info/WHEEL
imt_tree_utils-0.2.7.dist-info/top_level.txt
imt_tree_utils-0.2.7.dist-info/RECORD
